pyapt/__init__.py
pyapt/static.py
pyapt/core/__init__.py
pyapt/core/core.py
pyapt-0.0.7.dist-info/LICENSE
pyapt-0.0.7.dist-info/METADATA
pyapt-0.0.7.dist-info/WHEEL
pyapt-0.0.7.dist-info/entry_points.txt
pyapt-0.0.7.dist-info/top_level.txt
pyapt-0.0.7.dist-info/RECORD
